.VERSION
AUTHORS.rst
CONTRIBUTING.rst
HISTORY.rst
LICENSE
MANIFEST.in
Pipfile
Pipfile.lock
README.rst
USAGE.rst
dev-requirements.txt
requirements.txt
setup.cfg
setup.py
docs/Makefile
docs/authors.rst
docs/conf.py
docs/contributing.rst
docs/history.rst
docs/index.rst
docs/installation.rst
docs/readme.rst
docs/usage.rst
gitwrapperlib/.VERSION
gitwrapperlib/AUTHORS.rst
gitwrapperlib/CONTRIBUTING.rst
gitwrapperlib/HISTORY.rst
gitwrapperlib/LICENSE
gitwrapperlib/Pipfile
gitwrapperlib/Pipfile.lock
gitwrapperlib/README.rst
gitwrapperlib/USAGE.rst
gitwrapperlib/__init__.py
gitwrapperlib/_version.py
gitwrapperlib/dev-requirements.txt
gitwrapperlib/gitwrapperlib.py
gitwrapperlib/gitwrapperlibexceptions.py
gitwrapperlib/requirements.txt
gitwrapperlib.egg-info/PKG-INFO
gitwrapperlib.egg-info/SOURCES.txt
gitwrapperlib.egg-info/dependency_links.txt
gitwrapperlib.egg-info/not-zip-safe
gitwrapperlib.egg-info/requires.txt
gitwrapperlib.egg-info/top_level.txt
gitwrapperlib/__pycache__/__init__.cpython-37.pyc
gitwrapperlib/__pycache__/__init__.cpython-39.pyc
gitwrapperlib/__pycache__/_version.cpython-37.pyc
gitwrapperlib/__pycache__/_version.cpython-39.pyc
gitwrapperlib/__pycache__/gitwrapperlib.cpython-37.pyc
gitwrapperlib/__pycache__/gitwrapperlib.cpython-39.pyc
gitwrapperlib/__pycache__/gitwrapperlibexceptions.cpython-37.pyc
gitwrapperlib/__pycache__/gitwrapperlibexceptions.cpython-39.pyc
tests/test_gitwrapperlib.py