Metadata-Version: 2.1
Name: gitwrapperlib
Version: 1.0.4
Summary: A lightweight wrapper around the git command using sh module.
Home-page: https://github.com/costastf/gitwrapperlib
Author: Costas Tyfoxylos
Author-email: costas.tyf@gmail.com
License: MIT
Keywords: gitwrapperlib git python sh
Classifier: Development Status :: 4 - Beta
Classifier: Intended Audience :: Developers
Classifier: License :: OSI Approved :: MIT License
Classifier: Natural Language :: English
Classifier: Programming Language :: Python :: 3.7
License-File: LICENSE
License-File: AUTHORS.rst
Requires-Dist: sh>=2.0.4; sys_platform != "win32"
Requires-Dist: pbs~=0.110; sys_platform == "win32"
